lutron_homeworks/__init__.py
lutron_homeworks/client.py
lutron_homeworks/devices.py
lutron_homeworks/events.py
lutron_homeworks/exceptions.py
lutron_homeworks/message.py
lutron_homeworks/protocol.py
lutron_homeworks-1.0.4.dist-info/LICENSE
lutron_homeworks-1.0.4.dist-info/METADATA
lutron_homeworks-1.0.4.dist-info/WHEEL
lutron_homeworks-1.0.4.dist-info/top_level.txt
lutron_homeworks-1.0.4.dist-info/RECORD
